LICENSE
README.md
setup.cfg
setup.py
celebrity_births_erikh.egg-info/PKG-INFO
celebrity_births_erikh.egg-info/SOURCES.txt
celebrity_births_erikh.egg-info/dependency_links.txt
celebrity_births_erikh.egg-info/requires.txt
celebrity_births_erikh.egg-info/top_level.txt
project/__init__.py
project/celebrities_births_erikh.py
project/wiki_celebrities_erikh.py
test/test_date.py