Metadata-Version: 2.1
Name: celebrity-births-erikh
Version: 0.0.1
Summary: Mock package that allows you to find celebrity by date of birth
Home-page: https://github.com/eharaldson/project-structure-mini-challenge-1.git
Author: Erik Haraldson
License: Oxford
Platform: UNKNOWN
License-File: LICENSE
